brainglobe_space/__init__.py
brainglobe_space/core.py
brainglobe_space/functions.py
brainglobe_space/utils.py
brainglobe_space-1.0.3.dist-info/LICENSE
brainglobe_space-1.0.3.dist-info/METADATA
brainglobe_space-1.0.3.dist-info/WHEEL
brainglobe_space-1.0.3.dist-info/top_level.txt
brainglobe_space-1.0.3.dist-info/RECORD
