Metadata-Version: 2.2
Name: brainglobe_space
Version: 1.0.3
Summary: Anatomical space conventions made easy
Author-email: Luigi Petrucco <luigi.petrucco@gmail.com>
Project-URL: Homepage, https://github.com/brainglobe/brainglobe-space
Classifier: Development Status :: 3 - Alpha
Classifier: Intended Audience :: Science/Research
Classifier: Operating System :: OS Independent
Classifier: Programming Language :: Python
Classifier: Programming Language :: Python :: 3
Classifier: Programming Language :: Python :: 3.10
Classifier: Programming Language :: Python :: 3.11
Classifier: Programming Language :: Python :: 3.12
Requires-Python: >=3.10
License-File: LICENSE
Requires-Dist: numpy
Requires-Dist: scipy
Provides-Extra: dev
Requires-Dist: gitpython; extra == "dev"
Requires-Dist: pre-commit; extra == "dev"
Requires-Dist: pytest; extra == "dev"
Requires-Dist: pytest-cov; extra == "dev"
